yta_video_advanced_effects/__init__.py
yta_video_advanced_effects/filters/__init__.py
yta_video_advanced_effects/filters/ascii_filtered_video.py
yta_video_advanced_effects/filters/colored_ascii_filtered_video.py
yta_video_advanced_effects/filters/frame.py
yta_video_advanced_effects/filters/pixelate.py
yta_video_advanced_effects/filters/pixelated_video.py
yta_video_advanced_effects/filters/sketch.py
yta_video_advanced_effects/filters/video.py
yta_video_advanced_effects/m_effect/__init__.py
yta_video_advanced_effects/m_effect/black_and_white_effect.py
yta_video_advanced_effects/m_effect/blink_effect.py
yta_video_advanced_effects/m_effect/blur_effect.py
yta_video_advanced_effects/m_effect/constants.py
yta_video_advanced_effects/m_effect/fade_in_effect.py
yta_video_advanced_effects/m_effect/fade_out_effect.py
yta_video_advanced_effects/m_effect/fit_duration_effect.py
yta_video_advanced_effects/m_effect/flip_horizontally_effect.py
yta_video_advanced_effects/m_effect/flip_vertically_effect.py
yta_video_advanced_effects/m_effect/freeze_first_frame_effect.py
yta_video_advanced_effects/m_effect/freeze_last_frame_effect.py
yta_video_advanced_effects/m_effect/handmade/__init__.py
yta_video_advanced_effects/m_effect/handmade/dynamic_postcard_effect.py
yta_video_advanced_effects/m_effect/handmade/zoom_in_display_and_zoom_out_effect.py
yta_video_advanced_effects/m_effect/multiplied_effect.py
yta_video_advanced_effects/m_effect/photo_is_taken_effect.py
yta_video_advanced_effects/m_effect/reversed_effect.py
yta_video_advanced_effects/m_effect/sad_moment_effect.py
yta_video_advanced_effects/m_effect/scroll_effect.py
yta_video_advanced_effects/m_effect/stop_motion_effect.py
yta_video_advanced_effects/m_effect/zoom_out_on_video_position_effect.py
yta_video_advanced_effects/m_effect/zoom_video_effect.py
yta_video_advanced_effects/moviepy/__init__.py
yta_video_advanced_effects/moviepy/alpha.py
yta_video_advanced_effects/moviepy/objects.py
yta_video_advanced_effects-0.0.3.dist-info/LICENSE
yta_video_advanced_effects-0.0.3.dist-info/METADATA
yta_video_advanced_effects-0.0.3.dist-info/WHEEL
yta_video_advanced_effects-0.0.3.dist-info/RECORD
